cleft/__init__.py
cleft/utils/__init__.py
cleft/utils/blindscribe.py
cleft/utils/core.py
cleft/utils/cryptex.py
cleft/utils/listen.py
cleft/utils/note.py
cleft/utils/portland.py
cleft/utils/pprint.py
cleft/utils/replacer.py
cleft/utils/.ipynb_checkpoints/numeric-checkpoint.py
cleft/utils/llm/__init__.py
cleft/utils/llm/chatgpt.py
cleft/utils/llm/claude.py
cleft/utils/llm/interfaces.py
cleft/utils/llm/models.py
cleft-0.0.0.dev6.dist-info/METADATA
cleft-0.0.0.dev6.dist-info/WHEEL
cleft-0.0.0.dev6.dist-info/entry_points.txt
cleft-0.0.0.dev6.dist-info/RECORD
